pama_ex/.DS_Store
pama_ex/__init__.py
pama_ex/client.py
pama_ex-0.1.0.dist-info/WHEEL
pama_ex-0.1.0.dist-info/METADATA
pama_ex-0.1.0.dist-info/RECORD
