Metadata-Version: 2.4
Name: pama_ex
Version: 0.1.0
Summary: Пакет pama_ex для работы с API.
Author: ALEX_PAST
